device_fingerprinting/__init__.py
device_fingerprinting/analytics_dashboard.py
device_fingerprinting/backends.py
device_fingerprinting/cloud_features.py
device_fingerprinting/crypto.py
device_fingerprinting/default_backends.py
device_fingerprinting/device_fingerprinting.py
device_fingerprinting/exceptions.py
device_fingerprinting/forensic_security.py
device_fingerprinting/hsm_backends.py
device_fingerprinting/hybrid_pqc.py
device_fingerprinting/ml_features.py
device_fingerprinting/production_fingerprint.py
device_fingerprinting/quantum_crypto.py
device_fingerprinting/quantum_resistant_backends.py
device_fingerprinting/rust_bridge.py
device_fingerprinting/secure_storage.py
device_fingerprinting/security.py
device_fingerprinting/tpm_hardware.py
device_fingerprinting/version.py
device_fingerprinting_pro-2.2.3.dist-info/licenses/LICENSE
device_fingerprinting_pro-2.2.3.dist-info/METADATA
device_fingerprinting_pro-2.2.3.dist-info/WHEEL
device_fingerprinting_pro-2.2.3.dist-info/top_level.txt
device_fingerprinting_pro-2.2.3.dist-info/RECORD
