Metadata-Version: 2.4
Name: device-fingerprinting-pro
Version: 2.2.3
Summary: Hardware device fingerprinting with post-quantum cryptography, TPM support, and ML-based anomaly detection
Author-email: Johnsonajibi <ajibijohnson@jtnetsolutions.com>
Maintainer-email: Johnsonajibi <ajibijohnson@jtnetsolutions.com>
License-Expression: MIT
Project-URL: Homepage, https://github.com/Johnsonajibi/DeviceFingerprinting
Project-URL: Documentation, https://device-fingerprinting.readthedocs.io
Project-URL: Repository, https://github.com/Johnsonajibi/DeviceFingerprinting
Project-URL: Issues, https://github.com/Johnsonajibi/DeviceFingerprinting/issues
Project-URL: Changelog, https://github.com/Johnsonajibi/DeviceFingerprinting/blob/main/CHANGELOG.md
Keywords: device-fingerprinting,hardware-fingerprinting,tpm,trusted-platform-module,machine-learning,anomaly-detection,device-binding,software-licensing,encryption,security,post-quantum-cryptography
Classifier: Development Status :: 5 - Production/Stable
Classifier: Intended Audience :: Developers
Classifier: Operating System :: OS Independent
Classifier: Programming Language :: Python :: 3
Classifier: Programming Language :: Python :: 3.9
Classifier: Programming Language :: Python :: 3.10
Classifier: Programming Language :: Python :: 3.11
Classifier: Programming Language :: Python :: 3.12
Classifier: Topic :: Security :: Cryptography
Classifier: Topic :: Software Development :: Libraries :: Python Modules
Classifier: Topic :: System :: Hardware
Classifier: Topic :: Scientific/Engineering :: Artificial Intelligence
Classifier: Typing :: Typed
Requires-Python: >=3.9
License-File: LICENSE
Requires-Dist: numpy>=1.21.0
Requires-Dist: scikit-learn>=1.0.0
Requires-Dist: psutil>=5.8.0
Requires-Dist: cryptography>=43.0.0
Requires-Dist: keyring>=23.0.0
Requires-Dist: certifi>=2024.7.4
Provides-Extra: pqc
Requires-Dist: pqcdualusb>=0.15.5; extra == "pqc"
Provides-Extra: cloud
Requires-Dist: boto3>=1.28.0; extra == "cloud"
Requires-Dist: azure-storage-blob>=12.17.0; extra == "cloud"
Provides-Extra: dev
Requires-Dist: pytest>=7.0.0; extra == "dev"
Requires-Dist: pytest-cov>=4.0.0; extra == "dev"
Requires-Dist: pytest-mock>=3.10.0; extra == "dev"
Requires-Dist: black>=23.0.0; extra == "dev"
Requires-Dist: flake8>=6.0.0; extra == "dev"
Requires-Dist: mypy>=1.0.0; extra == "dev"
Requires-Dist: isort>=5.12.0; extra == "dev"
Requires-Dist: pre-commit>=3.0.0; extra == "dev"
Provides-Extra: docs
Requires-Dist: sphinx>=6.0.0; extra == "docs"
Requires-Dist: sphinx-rtd-theme>=1.2.0; extra == "docs"
Requires-Dist: sphinx-autodoc-typehints>=1.22.0; extra == "docs"
Provides-Extra: test
Requires-Dist: pytest>=7.0.0; extra == "test"
Requires-Dist: pytest-cov>=4.0.0; extra == "test"
Requires-Dist: pytest-mock>=3.10.0; extra == "test"
Requires-Dist: tox>=4.0.0; extra == "test"
Dynamic: license-file
